Products.ResourceRegistries-3.0.8-py2.7-nspkg.pth
Products/ResourceRegistries/__init__.py
Products/ResourceRegistries/config.py
Products/ResourceRegistries/configure.zcml
Products/ResourceRegistries/permissions.py
Products/ResourceRegistries/tool.gif
Products/ResourceRegistries/utils.py
Products/ResourceRegistries/browser/__init__.py
Products/ResourceRegistries/browser/configure.zcml
Products/ResourceRegistries/browser/interfaces.py
Products/ResourceRegistries/browser/kss.pt
Products/ResourceRegistries/browser/kss.py
Products/ResourceRegistries/browser/resourceregistries.pt
Products/ResourceRegistries/browser/scripts.pt
Products/ResourceRegistries/browser/scripts.py
Products/ResourceRegistries/browser/styles.pt
Products/ResourceRegistries/browser/styles.py
Products/ResourceRegistries/exportimport/__init__.py
Products/ResourceRegistries/exportimport/configure.zcml
Products/ResourceRegistries/exportimport/cssregistry.py
Products/ResourceRegistries/exportimport/jsregistry.py
Products/ResourceRegistries/exportimport/kssregistry.py
Products/ResourceRegistries/exportimport/resourceregistry.py
Products/ResourceRegistries/interfaces/__init__.py
Products/ResourceRegistries/interfaces/registries.py
Products/ResourceRegistries/interfaces/settings.py
Products/ResourceRegistries/interfaces/viewletmanagers.py
Products/ResourceRegistries/tools/BaseRegistry.py
Products/ResourceRegistries/tools/CSSRegistry.py
Products/ResourceRegistries/tools/JSRegistry.py
Products/ResourceRegistries/tools/KSSRegistry.py
Products/ResourceRegistries/tools/__init__.py
Products/ResourceRegistries/tools/packer.py
Products/ResourceRegistries/www/bundles.zpt
Products/ResourceRegistries/www/csscomposition.zpt
Products/ResourceRegistries/www/cssconfig.zpt
Products/ResourceRegistries/www/jscomposition.zpt
Products/ResourceRegistries/www/jsconfig.zpt
Products/ResourceRegistries/www/ksscomposition.zpt
Products/ResourceRegistries/www/kssconfig.zpt
Products.ResourceRegistries-3.0.8.dist-info/METADATA
Products.ResourceRegistries-3.0.8.dist-info/WHEEL
Products.ResourceRegistries-3.0.8.dist-info/namespace_packages.txt
Products.ResourceRegistries-3.0.8.dist-info/top_level.txt
Products.ResourceRegistries-3.0.8.dist-info/RECORD
