Metadata-Version: 2.1
Name: Products.ResourceRegistries
Version: 3.0.8
Summary: Registry for managing CSS and JS
Home-page: https://pypi.org/project/Products.ResourceRegistries
Author: Plone Foundation
Author-email: plone-developers@lists.sourceforge.net
License: GPL version 2
Keywords: CSS Javascript Zope Packer
Platform: UNKNOWN
Classifier: Development Status :: 6 - Mature
Classifier: Environment :: Web Environment
Classifier: Framework :: Plone
Classifier: Framework :: Plone :: 5.0
Classifier: Framework :: Plone :: 5.1
Classifier: Framework :: Zope2
Classifier: License :: OSI Approved :: GNU General Public License v2 (GPLv2)
Classifier: Operating System :: OS Independent
Classifier: Programming Language :: Python
Classifier: Programming Language :: Python :: 2.7
Classifier: Topic :: Software Development :: Pre-processors
Requires-Dist: setuptools
Requires-Dist: six
Requires-Dist: zope.component
Requires-Dist: zope.interface
Requires-Dist: zope.viewlet
Requires-Dist: Products.CMFCore
Requires-Dist: plone.protect (>=3.0.0a1)
Requires-Dist: Products.GenericSetup
Requires-Dist: Acquisition
Requires-Dist: DateTime
Requires-Dist: ZODB3
Requires-Dist: Zope2
Requires-Dist: plone.app.registry
Provides-Extra: test
Requires-Dist: zope.contentprovider ; extra == 'test'
